{"zh_index.md":"hIVuAM2k","zh_develop_structure.md":"GaVHDB8y","en_guide_cli-generator.md":"DqksErPb","en_index.md":"0sGph4EK","zh_guide_build-on-windows.md":"8chypmxG","zh_guide_extension-notes.md":"C7ypEWon","zh_develop_index.md":"f5XM1pgw","zh_guide_extensions.md":"nWB2A5Cz","extension-notes.md":"CKFwTuBz","en_guide_index.md":"SjJ5oI1w","zh_guide_cli-generator.md":"aFI4qKil","zh_develop_system-build-tools.md":"msWI0j7y","en_guide_extensions.md":"6W2jPYmj","index.md":"-W9YoVPe","zh_guide_index.md":"rq1-JSxT","en_guide_build-on-windows.md":"M8zmPfnU","en_guide_action-build.md":"WVX5RHcU","zh_guide_action-build.md":"R6PG_gv9","en_guide_troubleshooting.md":"3wplQVMM","en_develop_source-module.md":"1FLWeQiQ","zh_guide_troubleshooting.md":"l3UXzYj1","zh_faq_index.md":"v_lrg-Bi","en_develop_doctor-module.md":"tvsWwFbz","zh_guide_manual-build.md":"t8yLQYeK","en_contributing_index.md":"jdDe14oW","zh_contributing_index.md":"godHuxJo","en_develop_structure.md":"l-Q5f7oe","en_develop_index.md":"c13pu7-e","en_develop_system-build-tools.md":"BMwNCusx","zh_develop_source-module.md":"0drxipGd","en_guide_manual-build.md":"Hrwtk_Kd","en_faq_index.md":"rdHnvn8z","extensions.md":"P8hcaa95","zh_develop_doctor-module.md":"Ft9M8dQZ","en_guide_extension-notes.md":"f9POVFvx"}
