{"extension-notes.md":"CKFwTuBz","en_guide_extension-notes.md":"G6kt6tUy","zh_guide_action-build.md":"H8HtRqWn","index.md":"-W9YoVPe","zh_guide_cli-generator.md":"lfwXYetb","zh_develop_index.md":"f5XM1pgw","zh_develop_system-build-tools.md":"tLZULKrT","en_develop_system-build-tools.md":"SRqdXF12","en_guide_index.md":"SjJ5oI1w","en_faq_index.md":"rdHnvn8z","en_guide_action-build.md":"WVX5RHcU","zh_guide_extensions.md":"jKoc5oAZ","en_index.md":"0sGph4EK","en_guide_build-on-windows.md":"Tnm_im5I","extensions.md":"lMueZXYm","zh_faq_index.md":"v_lrg-Bi","zh_contributing_index.md":"godHuxJo","en_guide_troubleshooting.md":"3wplQVMM","en_develop_source-module.md":"1FLWeQiQ","zh_guide_index.md":"rq1-JSxT","zh_develop_structure.md":"GaVHDB8y","en_guide_cli-generator.md":"27qYzStz","zh_index.md":"hIVuAM2k","en_develop_index.md":"c13pu7-e","zh_guide_troubleshooting.md":"l3UXzYj1","zh_guide_build-on-windows.md":"rebhkrHT","en_contributing_index.md":"jdDe14oW","en_develop_doctor-module.md":"tvsWwFbz","en_develop_structure.md":"l-Q5f7oe","zh_guide_manual-build.md":"BAZi8pUI","zh_develop_doctor-module.md":"Ft9M8dQZ","zh_guide_extension-notes.md":"66__QJbb","en_guide_manual-build.md":"Szh8l33g","en_guide_extensions.md":"8EYVJSeb","zh_develop_source-module.md":"0drxipGd"}
