{"en_develop_index.md":"DpXFrPSW","zh_develop_system-build-tools.md":"BcSEvLWq","en_guide_cli-generator.md":"Di6fCTkN","zh_faq_index.md":"DzybCGmE","en_guide_env-vars.md":"uwjapWk-","en_faq_index.md":"BVyZnjBj","en_guide_extension-notes.md":"nR2uVBsd","en_guide_extensions.md":"Dq3anKcp","zh_guide_action-build.md":"BdoXFRC0","en_index.md":"BUfMQ6rb","zh_guide_extension-notes.md":"DlxOQhU8","en_develop_system-build-tools.md":"CEtH7ZDM","extension-notes.md":"jzIo6LDw","zh_guide_extensions.md":"6DSDoqSw","zh_develop_source-module.md":"BgmofhY1","zh_develop_structure.md":"BKo1eXYT","zh_contributing_index.md":"COUOrvr5","zh_develop_doctor-module.md":"1zI3NHLP","zh_guide_env-vars.md":"BtevEgOs","en_guide_index.md":"BHNXifuG","en_guide_action-build.md":"D4sK_4FO","zh_guide_index.md":"B-3jYE0-","zh_guide_troubleshooting.md":"Bqj2SVrP","index.md":"D-mm_nya","zh_index.md":"DpfrTEU3","en_develop_source-module.md":"CetY2l0z","en_guide_manual-build.md":"BsRuOteN","en_guide_build-on-windows.md":"BfWaQWNz","zh_guide_manual-build.md":"BQaneRSl","zh_guide_build-on-windows.md":"CA6k7NVv","en_develop_structure.md":"DV_1s770","zh_develop_index.md":"DjGoZ0WL","en_guide_troubleshooting.md":"SCdTjpCB","zh_guide_cli-generator.md":"Cm8Sb6rD","en_contributing_index.md":"DZraZA7y","extensions.md":"DZpapmcm","en_develop_doctor-module.md":"DC_o8-Ms"}
